wurm/__init__.py
wurm/connection.py
wurm/queries.py
wurm/sql.py
wurm/tables.py
wurm/typemaps.py
wurm-0.1.0.dist-info/METADATA
wurm-0.1.0.dist-info/RECORD
wurm-0.1.0.dist-info/WHEEL
wurm-0.1.0.dist-info/top_level.txt
