Metadata-Version: 2.1
Name: wurm
Version: 0.1.0
Summary: Simple sqlite3-based ORM
Home-page: https://github.com/gvx/wurm
Author: Jasmijn Wellner
Author-email: gyvox.public@gmail.com
Maintainer: Jasmijn Wellner
Maintainer-email: gyvox.public@gmail.com
License: MIT
Platform: UNKNOWN
Classifier: Development Status :: 4 - Beta
Classifier: Intended Audience :: Developers
Classifier: License :: OSI Approved :: MIT License
Classifier: Natural Language :: English
Classifier: Operating System :: OS Independent
Classifier: Programming Language :: Python :: 3.7
Classifier: Programming Language :: Python :: 3.8
Classifier: Programming Language :: Python :: 3.9
Requires-Dist: typing-extensions; python_version < "3.9.0"
